lightspeed_stack_providers/__init__.py
lightspeed_stack_providers/providers/__init__.py
lightspeed_stack_providers/providers/inline/__init__.py
lightspeed_stack_providers/providers/inline/agents/__init__.py
lightspeed_stack_providers/providers/inline/agents/lightspeed_inline_agent/__init__.py
lightspeed_stack_providers/providers/inline/agents/lightspeed_inline_agent/agent_instance.py
lightspeed_stack_providers/providers/inline/agents/lightspeed_inline_agent/agents.py
lightspeed_stack_providers/providers/inline/agents/lightspeed_inline_agent/config.py
lightspeed_stack_providers/providers/inline/safety/__init__.py
lightspeed_stack_providers/providers/inline/safety/lightspeed_question_validity/__init__.py
lightspeed_stack_providers/providers/inline/safety/lightspeed_question_validity/config.py
lightspeed_stack_providers/providers/inline/safety/lightspeed_question_validity/safety.py
lightspeed_stack_providers/providers/inline/safety/lightspeed_redaction/lightspeed_redaction/__init__.py
lightspeed_stack_providers/providers/inline/safety/lightspeed_redaction/lightspeed_redaction/config.py
lightspeed_stack_providers/providers/inline/safety/lightspeed_redaction/lightspeed_redaction/redaction.py
lightspeed_stack_providers/providers/remote/__init__.py
lightspeed_stack_providers/providers/remote/agents/__init__.py
lightspeed_stack_providers/providers/remote/agents/lightspeed_agent/__init__.py
lightspeed_stack_providers/providers/remote/agents/lightspeed_agent/config.py
lightspeed_stack_providers/providers/remote/agents/lightspeed_agent/lightspeed.py
lightspeed_stack_providers/providers/remote/tool_runtime/__init__.py
lightspeed_stack_providers/providers/remote/tool_runtime/lightspeed/__init__.py
lightspeed_stack_providers/providers/remote/tool_runtime/lightspeed/config.py
lightspeed_stack_providers/providers/remote/tool_runtime/lightspeed/lightspeed.py
lightspeed_stack_providers-0.1.18.dist-info/licenses/LICENSE
tests/features/environment.py
tests/features/steps/common_steps.py
tests/features/steps/question_validity_steps.py
lightspeed_stack_providers-0.1.18.dist-info/METADATA
lightspeed_stack_providers-0.1.18.dist-info/WHEEL
lightspeed_stack_providers-0.1.18.dist-info/top_level.txt
lightspeed_stack_providers-0.1.18.dist-info/RECORD
