Metadata-Version: 2.4
Name: lightspeed_stack_providers
Version: 0.1.18
Summary: Lightspeed Stack providers for llama-stack
Requires-Python: >=3.12
License-File: LICENSE
Requires-Dist: llama-stack==0.2.22
Requires-Dist: llama-stack-client==0.2.22
Requires-Dist: httpx
Requires-Dist: pydantic>=2.10.6
Requires-Dist: litellm>=1.75.5.post1
Requires-Dist: sqlalchemy>=2.0.0
Requires-Dist: mcp
Provides-Extra: dev
Requires-Dist: black>=25.1.0; extra == "dev"
Requires-Dist: ruff>=0.8.0; extra == "dev"
Provides-Extra: test
Requires-Dist: behave>=1.2.6; extra == "test"
Requires-Dist: requests>=2.31.0; extra == "test"
Requires-Dist: parse>=1.19.0; extra == "test"
Requires-Dist: parse-type>=0.6.0; extra == "test"
Requires-Dist: pytest>=8.3.2; extra == "test"
Requires-Dist: pytest-cov>=5.0.0; extra == "test"
Requires-Dist: pytest-mock>=3.14.0; extra == "test"
Requires-Dist: pytest-asyncio>=1.0.0; extra == "test"
Dynamic: license-file
